bandwidth_numbers/__init__.py
bandwidth_numbers/client.py
bandwidth_numbers/include/__init__.py
bandwidth_numbers/include/xml_consts.py
bandwidth_numbers/models/__init__.py
bandwidth_numbers/models/account.py
bandwidth_numbers/models/account_users.py
bandwidth_numbers/models/activation_status.py
bandwidth_numbers/models/available_npa_nxx.py
bandwidth_numbers/models/available_numbers.py
bandwidth_numbers/models/base_resource.py
bandwidth_numbers/models/cities.py
bandwidth_numbers/models/covered_rate_centers.py
bandwidth_numbers/models/disc_numbers.py
bandwidth_numbers/models/disconnect.py
bandwidth_numbers/models/disconnect_order_response.py
bandwidth_numbers/models/disconnects.py
bandwidth_numbers/models/dlda.py
bandwidth_numbers/models/dlda_order_response.py
bandwidth_numbers/models/dldas.py
bandwidth_numbers/models/file_meta_data.py
bandwidth_numbers/models/history.py
bandwidth_numbers/models/import_tn_checker.py
bandwidth_numbers/models/import_tn_checker_response.py
bandwidth_numbers/models/in_service_numbers.py
bandwidth_numbers/models/lidb.py
bandwidth_numbers/models/lidbs.py
bandwidth_numbers/models/line_option_order_response.py
bandwidth_numbers/models/line_option_orders.py
bandwidth_numbers/models/lnpchecker.py
bandwidth_numbers/models/lnpchecker_response.py
bandwidth_numbers/models/loas.py
bandwidth_numbers/models/messaging_settings.py
bandwidth_numbers/models/movetns.py
bandwidth_numbers/models/note.py
bandwidth_numbers/models/notes.py
bandwidth_numbers/models/order.py
bandwidth_numbers/models/order_history.py
bandwidth_numbers/models/order_response.py
bandwidth_numbers/models/order_tns.py
bandwidth_numbers/models/orders.py
bandwidth_numbers/models/password.py
bandwidth_numbers/models/portin.py
bandwidth_numbers/models/portins.py
bandwidth_numbers/models/portout.py
bandwidth_numbers/models/portouts.py
bandwidth_numbers/models/rate_center.py
bandwidth_numbers/models/rate_centers.py
bandwidth_numbers/models/reservation.py
bandwidth_numbers_sdk-1.1.0.dist-info/LICENSE
bandwidth_numbers_sdk-1.1.0.dist-info/METADATA
bandwidth_numbers_sdk-1.1.0.dist-info/WHEEL
bandwidth_numbers_sdk-1.1.0.dist-info/top_level.txt
bandwidth_numbers_sdk-1.1.0.dist-info/RECORD
