Metadata-Version: 2.1
Name: bandwidth-numbers-sdk
Version: 1.1.0
Summary: Bandwidth Numbers SDK
Home-page: https://github.com/bandwidth/python-numbers-sdk
Author: Bandwidth
Author-email: letstalk@bandwidth.com
License: UNKNOWN
Keywords: Bandwidth,Numbers
Platform: UNKNOWN
Requires-Python: >=3.7
License-File: LICENSE
Requires-Dist: certifi (==2019.11.28)
Requires-Dist: chardet (==3.0.4)
Requires-Dist: future (==1.0.0)
Requires-Dist: idna (==2.8)
Requires-Dist: requests (==2.32.3)
Requires-Dist: six (==1.16.0)
Requires-Dist: urllib3 (==1.26.6)
